oaloader/__init__.py
oaloader/__main__.py
oaloader/command.py
oaloader/const.py
oaloader/core.py
oaloader/log.py
oaloader-0.4.4.dist-info/entry_points.txt
oaloader-0.4.4.dist-info/LICENSE
oaloader-0.4.4.dist-info/WHEEL
oaloader-0.4.4.dist-info/METADATA
oaloader-0.4.4.dist-info/RECORD
