Metadata-Version: 2.1
Name: oaloader
Version: 0.4.4
Summary: A handy tool to manage your office addins locally, you can use it for addin development or deploy your addins for your clients out of AppSource.
Home-page: https://github.com/elonzh/office-addin-sideloader
License: MIT
Keywords: Windows,Office
Author: elonzh
Author-email: elonzh@qq.com
Requires-Python: >=3.8,<4.0
Classifier: License :: OSI Approved :: MIT License
Classifier: Operating System :: Microsoft :: Windows
Classifier: Operating System :: Microsoft :: Windows :: Windows 10
Classifier: Operating System :: Microsoft :: Windows :: Windows 7
Classifier: Operating System :: Microsoft :: Windows :: Windows 8
Classifier: Operating System :: Microsoft :: Windows :: Windows 8.1
Classifier: Programming Language :: Python :: 3
Classifier: Programming Language :: Python :: 3.8
Classifier: Programming Language :: Python :: 3.9
Classifier: Topic :: Office/Business :: Office Suites
Classifier: Topic :: Software Development :: Build Tools
Requires-Dist: click (>=8.0.3,<9.0.0)
Requires-Dist: loguru (>=0.5.3,<0.6.0)
Requires-Dist: pywin32 (>=300,<301)
Requires-Dist: requests (>=2.26.0,<3.0.0)
Requires-Dist: tabulate (>=0.8.9,<0.9.0)
Requires-Dist: xmltodict (>=0.12.0,<0.13.0)
Project-URL: Repository, https://github.com/elonzh/office-addin-sideloader
